Workbook

Sheet Dashboard
A1: Policy Review Snapshot 保单检视摘要
A2: Auto-calculated from 'Client' and 'Policies'. Inforce and paid-up policies count toward coverage.
A3: Client 客户: | B3: =Client!B4 | D3: Review date 检视日期: | E3: =Client!B8
A5: Coverage area 保障类别 | B5: Existing 现有 (RM) | C5: Standard 标准 (RM) | D5: Gap 差距 (RM) | E5: Status 状态
A6: Life / Death 身故 | B6: =SUMIFS(Policies!$L$2:$L$100,Policies!$G$2:$G$100,"Inforce")+SUMIFS(Policies!$L$2:$L$100,Policies!$G$2:$G$100,"Paid-up") | C6: =Client!B12 | D6: =MAX(0,C6-B6) | E6: =IF(C6=0,"-",IF(B6>=C6,"✔ On track 已达标","▲ Review 可加强"))
A7: TPD 完全永久残疾 | B7: =SUMIFS(Policies!$M$2:$M$100,Policies!$G$2:$G$100,"Inforce")+SUMIFS(Policies!$M$2:$M$100,Policies!$G$2:$G$100,"Paid-up") | C7: =Client!B13 | D7: =MAX(0,C7-B7) | E7: =IF(C7=0,"-",IF(B7>=C7,"✔ On track 已达标","▲ Review 可加强"))
A8: Critical Illness 严重疾病 | B8: =SUMIFS(Policies!$N$2:$N$100,Policies!$G$2:$G$100,"Inforce")+SUMIFS(Policies!$N$2:$N$100,Policies!$G$2:$G$100,"Paid-up") | C8: =Client!B14 | D8: =MAX(0,C8-B8) | E8: =IF(C8=0,"-",IF(B8>=C8,"✔ On track 已达标","▲ Review 可加强"))
A9: Retirement fund (plans + EPF + PRS) 退休金 | B9: =SUMIFS(Policies!$Y$2:$Y$100,Policies!$G$2:$G$100,"Inforce")+SUMIFS(Policies!$Y$2:$Y$100,Policies!$G$2:$G$100,"Paid-up")+N(Client!B21)+N(Client!B22) | C9: =Client!B15 | D9: =MAX(0,C9-B9) | E9: =IF(C9=0,"-",IF(B9>=C9,"✔ On track 已达标","▲ Review 可加强"))
A10: Medical annual limit (highest) 医药年限 | B10: =MAX(_xlfn.MAXIFS(Policies!$P$2:$P$100,Policies!$G$2:$G$100,"Inforce"),_xlfn.MAXIFS(Policies!$P$2:$P$100,Policies!$G$2:$G$100,"Paid-up")) | C10: =Client!B16 | D10: =MAX(0,C10-B10) | E10: =IF(C10=0,"-",IF(B10>=C10,"✔ On track 已达标","▲ Review 可加强"))
A11: Room & board (RM/day) 房租 | B11: =MAX(_xlfn.MAXIFS(Policies!$Q$2:$Q$100,Policies!$G$2:$G$100,"Inforce"),_xlfn.MAXIFS(Policies!$Q$2:$Q$100,Policies!$G$2:$G$100,"Paid-up")) | C11: =Client!B17 | D11: =MAX(0,C11-B11) | E11: =IF(C11=0,"-",IF(B11>=C11,"✔ On track 已达标","▲ Review 可加强"))
A12: Personal Accident 意外 | B12: =SUMIFS(Policies!$R$2:$R$100,Policies!$G$2:$G$100,"Inforce")+SUMIFS(Policies!$R$2:$R$100,Policies!$G$2:$G$100,"Paid-up") | C12: - | D12: - | E12: No standard set
A14: Premium 保费
A15: Total annual premium (inforce + paid-up) 年缴总保费 | B15: =SUMIFS(Policies!$AA$2:$AA$100,Policies!$G$2:$G$100,"Inforce")+SUMIFS(Policies!$AA$2:$AA$100,Policies!$G$2:$G$100,"Paid-up")
A16: Monthly equivalent 每月相当于 | B16: =B15/12
A17: % of annual income 占年收入 | B17: =IF(Client!B6>0,B15/Client!B6,0)
A18: Premium budget 保费预算 | B18: =Client!B18
A20: Housekeeping 资料检查
A21: Inforce / paid-up policies 有效保单 | B21: =COUNTIFS(Policies!$G$2:$G$100,"Inforce")+COUNTIFS(Policies!$G$2:$G$100,"Paid-up")
A22: Not inforce (excluded) 非有效保单 | B22: =COUNTA(Policies!$A$2:$A$100)-B21
A23: Inforce without nominee 未提名 | B23: =COUNTIFS(Policies!$G$2:$G$100,"Inforce",Policies!$T$2:$T$100,"",Policies!$A$2:$A$100,"<>")+COUNTIFS(Policies!$G$2:$G$100,"Paid-up",Policies!$T$2:$T$100,"",Policies!$A$2:$A$100,"<>")
A44: Disclaimer: Summary based on policy information provided as at review date. Benefits are subject to the terms of each policy contract. Review standards are planning benchmarks, not recommendations or official figures.

Sheet Client
A1: Client Info 客户资料
A2: Fill column B. Review standards are YOUR planning benchmarks, not official figures.
A4: Client Name | B4: TAN MEI LING (SAMPLE)
A5: Age | B5: 38
A6: Annual Income (RM) | B6: 96000
A7: No. of Dependants | B7: 2
A8: Review Date | B8: 46324
A9: Prepared By | B9: Goh Poh Yee
A11: Review standard 检视标准
A12: Life cover target (RM) | B12: 1000000 | C12: Review standard
A13: TPD cover target (RM) | C13: Leave blank if no TPD standard
A14: CI cover target (RM) | B14: 1000000 | C14: Review standard
A15: Retirement target (RM) | B15: 1000000 | C15: Review standard
A16: Medical annual limit target (RM) | B16: 1000000 | C16: Review standard
A17: Room & board target (RM/day) | B17: 200 | C17: Adjust per client
A18: Premium budget (% of income) | B18: 0.1 | C18: Adjust per client
A20: Retirement savings 退休储蓄
A21: EPF / KWSP balance (RM) | C21: Latest statement / i-Akaun
A22: PRS balance (RM) | C22: Latest PRS statement
A24: Contact 联络资料
A25: Phone 电话 | C25: Not shown on the client report
A26: Date of birth 生日
A29: Family members 家人 | C29: For birthdays and follow-up. Not shown on the client report.
A30: Name 姓名 | B30: Relationship 关系 | C30: Birthday 生日 | D30: Phone 电话 | E30: Notes 备注

Sheet Policies
A1: Policy No | B1: Insurer | C1: Plan Name | D1: Policy Type | E1: Life Assured | F1: Policy Owner | G1: Status | H1: Commencement Date | I1: Expiry Date | J1: Premium (RM) | K1: Payment Mode | L1: Death (RM) | M1: TPD (RM) | N1: Critical Illness (RM) | O1: Early CI (RM) | P1: Medical Annual Limit (RM) | Q1: Room & Board (RM/day) | R1: Personal Accident (RM) | S1: Waiver of Premium | T1: Nominee Name | U1: Nominee Relationship | V1: Nomination Type | W1: Purpose | X1: Notes | Y1: Retirement Fund (RM) | Z1: Trust Created | AA1: Annual Premium (auto)
A2: S-0001 | B2: Great Eastern Life | C2: Whole Life Plan (sample) | D2: Whole Life | E2: TAN MEI LING | F2: TAN MEI LING | G2: Inforce | H2: 42078 | I2: 68376 | J2: 250 | K2: Monthly | L2: 200000 | M2: 200000 | S2: Yes | T2: LEE WEI MING | U2: Husband | V2: Hibah | W2: Family income protection | AA2: =IF(J2="","",IFERROR(VALUE(SUBSTITUTE(SUBSTITUTE(J2,"RM",""),",",""))*IFERROR(INDEX({12,4,2,1,0},MATCH(K2,{"Monthly","Quarterly","Half-yearly","Yearly","Single"},0)),0),0))
A3: S-0002 | B3: Great Eastern Life | C3: Medical Investment-Linked (sample) | D3: Medical | E3: TAN MEI LING | F3: TAN MEI LING | G3: Inforce | H3: 43282 | I3: 68850 | J3: 280 | K3: Monthly | L3: 50000 | M3: 50000 | P3: 150000 | Q3: 150 | S3: No | W3: Hospital & surgery bills | X3: Nominee not recorded - to confirm | AA3: =IF(J3="","",IFERROR(VALUE(SUBSTITUTE(SUBSTITUTE(J3,"RM",""),",",""))*IFERROR(INDEX({12,4,2,1,0},MATCH(K3,{"Monthly","Quarterly","Half-yearly","Yearly","Single"},0)),0),0))
A4: S-0003 | B4: Other Insurer | C4: Critical Illness Plan (sample) | D4: Critical Illness | E4: TAN MEI LING | F4: TAN MEI LING | G4: Inforce | H4: 43840 | I4: 58450 | J4: RM 1,800.00 | K4: Yearly | L4: 100000 | N4: 100000 | S4: No | T4: WONG SIEW LAN | U4: Mother | V4: Beneficiary | W4: Income replacement if diagnosed with CI | AA4: =IF(J4="","",IFERROR(VALUE(SUBSTITUTE(SUBSTITUTE(J4,"RM",""),",",""))*IFERROR(INDEX({12,4,2,1,0},MATCH(K4,{"Monthly","Quarterly","Half-yearly","Yearly","Single"},0)),0),0))
A5: S-0004 | B5: Other Insurer | C5: Personal Accident (sample) | D5: Personal Accident | E5: TAN MEI LING | F5: TAN MEI LING | G5: Inforce | H5: 45047 | I5: 46508 | J5: 300 | K5: Yearly | R5: 100000 | S5: No | W5: Accident cover | X5: Yearly renewable | AA5: =IF(J5="","",IFERROR(VALUE(SUBSTITUTE(SUBSTITUTE(J5,"RM",""),",",""))*IFERROR(INDEX({12,4,2,1,0},MATCH(K5,{"Monthly","Quarterly","Half-yearly","Yearly","Single"},0)),0),0))
A6: S-0005 | B6: Great Eastern Life | C6: Education Endowment (sample) | D6: Endowment / Savings | E6: TAN MEI LING | F6: TAN MEI LING | G6: Lapsed | H6: 41153 | I6: 48458 | J6: 100 | K6: Monthly | L6: 30000 | S6: No | T6: LEE JIA HUI | U6: Daughter | V6: Beneficiary | W6: Child education fund | X6: Lapsed 2021 - discuss reinstatement? | AA6: =IF(J6="","",IFERROR(VALUE(SUBSTITUTE(SUBSTITUTE(J6,"RM",""),",",""))*IFERROR(INDEX({12,4,2,1,0},MATCH(K6,{"Monthly","Quarterly","Half-yearly","Yearly","Single"},0)),0),0))
AA7: =IF(J7="","",IFERROR(VALUE(SUBSTITUTE(SUBSTITUTE(J7,"RM",""),",",""))*IFERROR(INDEX({12,4,2,1,0},MATCH(K7,{"Monthly","Quarterly","Half-yearly","Yearly","Single"},0)),0),0))
AA8: =IF(J8="","",IFERROR(VALUE(SUBSTITUTE(SUBSTITUTE(J8,"RM",""),",",""))*IFERROR(INDEX({12,4,2,1,0},MATCH(K8,{"Monthly","Quarterly","Half-yearly","Yearly","Single"},0)),0),0))
AA9: =IF(J9="","",IFERROR(VALUE(SUBSTITUTE(SUBSTITUTE(J9,"RM",""),",",""))*IFERROR(INDEX({12,4,2,1,0},MATCH(K9,{"Monthly","Quarterly","Half-yearly","Yearly","Single"},0)),0),0))
AA10: =IF(J10="","",IFERROR(VALUE(SUBSTITUTE(SUBSTITUTE(J10,"RM",""),",",""))*IFERROR(INDEX({12,4,2,1,0},MATCH(K10,{"Monthly","Quarterly","Half-yearly","Yearly","Single"},0)),0),0))
AA11: =IF(J11="","",IFERROR(VALUE(SUBSTITUTE(SUBSTITUTE(J11,"RM",""),",",""))*IFERROR(INDEX({12,4,2,1,0},MATCH(K11,{"Monthly","Quarterly","Half-yearly","Yearly","Single"},0)),0),0))
AA12: =IF(J12="","",IFERROR(VALUE(SUBSTITUTE(SUBSTITUTE(J12,"RM",""),",",""))*IFERROR(INDEX({12,4,2,1,0},MATCH(K12,{"Monthly","Quarterly","Half-yearly","Yearly","Single"},0)),0),0))
AA13: =IF(J13="","",IFERROR(VALUE(SUBSTITUTE(SUBSTITUTE(J13,"RM",""),",",""))*IFERROR(INDEX({12,4,2,1,0},MATCH(K13,{"Monthly","Quarterly","Half-yearly","Yearly","Single"},0)),0),0))
AA14: =IF(J14="","",IFERROR(VALUE(SUBSTITUTE(SUBSTITUTE(J14,"RM",""),",",""))*IFERROR(INDEX({12,4,2,1,0},MATCH(K14,{"Monthly","Quarterly","Half-yearly","Yearly","Single"},0)),0),0))
AA15: =IF(J15="","",IFERROR(VALUE(SUBSTITUTE(SUBSTITUTE(J15,"RM",""),",",""))*IFERROR(INDEX({12,4,2,1,0},MATCH(K15,{"Monthly","Quarterly","Half-yearly","Yearly","Single"},0)),0),0))
AA16: =IF(J16="","",IFERROR(VALUE(SUBSTITUTE(SUBSTITUTE(J16,"RM",""),",",""))*IFERROR(INDEX({12,4,2,1,0},MATCH(K16,{"Monthly","Quarterly","Half-yearly","Yearly","Single"},0)),0),0))
AA17: =IF(J17="","",IFERROR(VALUE(SUBSTITUTE(SUBSTITUTE(J17,"RM",""),",",""))*IFERROR(INDEX({12,4,2,1,0},MATCH(K17,{"Monthly","Quarterly","Half-yearly","Yearly","Single"},0)),0),0))
AA18: =IF(J18="","",IFERROR(VALUE(SUBSTITUTE(SUBSTITUTE(J18,"RM",""),",",""))*IFERROR(INDEX({12,4,2,1,0},MATCH(K18,{"Monthly","Quarterly","Half-yearly","Yearly","Single"},0)),0),0))
... AA100: =IF(J100="","",IFERROR(VALUE(SUBSTITUTE(SUBSTITUTE(J100,"RM",""),",",""))*IFERROR(INDEX({12,4,2,1,0},MATCH(K100,{"Monthly","Quarterly","Half-yearly","Yearly","Single"},0)),0),0))

Sheet Review notes
A1: Review notes 检视记录
A2: Filled by the app: areas to discuss, data checks and the change log.

Sheet Guide
A1: HOW TO USE 使用方法
A2: 1. Client sheet: fill client name, income, review date. Review standard is RM1m for Life, CI, Retirement, Medical - adjust if needed.
A3: 2. Policies sheet: one row per policy. Use the dropdowns for Type, Status, Payment Mode.
A4: 3. Leave a cell BLANK if you don't know it. Never type a guess - the app flags blanks for you to confirm.
A5: 4. Dashboard sheet updates automatically (Excel-only version).
A6: 5. For the visual PDF report: open 'Policy Review Snapshot.html', load this file, click 'Generate'.
A8: Pink nominee cell = inforce policy without nominee recorded.
A9: Only Inforce policies count toward coverage totals. Lapsed/Paid-up are listed separately.
A10: The rows marked (sample) are fictional - delete them before using with a real client.

Sheet Lists
A1: Insurer (Malaysia life & family takaful)
A2: AIA
A3: Allianz Life
A4: AmMetLife
A5: Etiqa Life
A6: FWD Insurance
A7: Generali Life
A8: Great Eastern Life
A9: Hong Leong Assurance
A10: Manulife
A11: MCIS
A12: Prudential Assurance
... A26: Zurich Takaful
